redash_stmo/__init__.py
redash_stmo/dockerflow.py
redash_stmo/resources.py
redash_stmo/settings.py
redash_stmo/data_sources/__init__.py
redash_stmo/data_sources/health.py
redash_stmo/data_sources/details/__init__.py
redash_stmo/data_sources/details/extension.py
redash_stmo/data_sources/details/bundle/DataSourceDetails.jsx
redash_stmo/handlers/__init__.py
redash_stmo/handlers/authentication/__init__.py
redash_stmo/handlers/authentication/remote_user_auth.py
redash_stmo/handlers/query_results/__init__.py
redash_stmo/handlers/query_results/extension.py
redash_stmo/handlers/query_results/parser.py
redash_stmo/query_runner/__init__.py
redash_stmo/query_runner/activedata.py
redash_stmo/query_runner/big_query.py
redash_stmo/query_runner/presto.py
redash_stmo-2025.5.1.dist-info/LICENSE
redash_stmo-2025.5.1.dist-info/METADATA
redash_stmo-2025.5.1.dist-info/WHEEL
redash_stmo-2025.5.1.dist-info/entry_points.txt
redash_stmo-2025.5.1.dist-info/top_level.txt
redash_stmo-2025.5.1.dist-info/RECORD
