Metadata-Version: 2.1
Name: redash-stmo
Version: 2025.5.1
Summary: Extensions to Redash by Mozilla
Author: Mozilla Foundation
Author-email: dev-webdev@lists.mozilla.org
License: MPL-2.0
Project-URL: homepage, https://github.com/mozilla/redash-stmo
Classifier: Development Status :: 5 - Production/Stable
Classifier: Environment :: Web Environment :: Mozilla
Classifier: Framework :: Django
Classifier: Intended Audience :: Developers
Classifier: License :: OSI Approved :: Mozilla Public License 2.0 (MPL 2.0)
Classifier: Programming Language :: Python
Classifier: Programming Language :: Python :: 3
Classifier: Programming Language :: Python :: 3.7
Classifier: Topic :: Internet :: WWW/HTTP
Requires-Python: >=3.5, <4
License-File: LICENSE
Requires-Dist: dockerflow >=2018.4.0
Requires-Dist: pyhive
Requires-Dist: requests
Requires-Dist: sqlparse
Provides-Extra: dev
Requires-Dist: watchdog[watchmedo] ; extra == 'dev'
Provides-Extra: test
Requires-Dist: flake8 ==3.5.0 ; extra == 'test'
Requires-Dist: importlib-metadata <5.0.0,>=1.6 ; extra == 'test'
Requires-Dist: mock ; extra == 'test'
Requires-Dist: pytest ; extra == 'test'
Requires-Dist: pytest-cov ; extra == 'test'
Requires-Dist: pytest-flake8 >=1.0.5 ; extra == 'test'
